{"per:countries_of_residence": 0, "per:city_of_birth": 1, "org:country_of_headquarters": 2, "per:title": 3, "org:member_of": 4, "per:other_family": 5, "org:city_of_headquarters": 6, "per:stateorprovinces_of_residence": 7, "per:spouse": 8, "org:parents": 9, "org:founded_by": 10, "org:shareholders": 11, "per:alternate_names": 12, "org:alternate_names": 13, "org:website": 14, "per:parents": 15, "per:country_of_death": 16, "org:founded": 17, "per:charges": 18, "per:children": 19, "org:members": 20, "per:origin": 21, "per:country_of_birth": 22, "per:date_of_birth": 23, "org:top_members/employees": 24, "org:subsidiaries": 25, "per:employee_of": 26, "org:number_of_employees/members": 27, "org:political/religious_affiliation": 28, "org:stateorprovince_of_headquarters": 29, "per:date_of_death": 30, "per:cause_of_death": 31, "per:schools_attended": 32, "org:dissolved": 33, "per:city_of_death": 34, "per:age": 35, "per:siblings": 36, "per:cities_of_residence": 37, "per:stateorprovince_of_death": 38, "per:religion": 39, "per:stateorprovince_of_birth": 40}